FlarumZhongwenWendang/README.md
FlarumZhongwenWendang/__init__.py
FlarumZhongwenWendang/__main__.py
FlarumZhongwenWendang/file.epub
FlarumZhongwenWendang/index.html
FlarumZhongwenWendang/css/__init__.py
FlarumZhongwenWendang/css/annotations.css
FlarumZhongwenWendang/css/main.css
FlarumZhongwenWendang/css/normalize.css
FlarumZhongwenWendang/css/popup.css
FlarumZhongwenWendang/font/__init__.py
FlarumZhongwenWendang/font/fontello.eot
FlarumZhongwenWendang/font/fontello.svg
FlarumZhongwenWendang/font/fontello.ttf
FlarumZhongwenWendang/font/fontello.woff
FlarumZhongwenWendang/img/__init__.py
FlarumZhongwenWendang/img/annotator-glyph-sprite.png
FlarumZhongwenWendang/img/annotator-icon-sprite.png
FlarumZhongwenWendang/img/apple-touch-icon.png
FlarumZhongwenWendang/img/cancelfullscreen.png
FlarumZhongwenWendang/img/close.png
FlarumZhongwenWendang/img/fullscreen.png
FlarumZhongwenWendang/img/loader.gif
FlarumZhongwenWendang/img/menu-icon.png
FlarumZhongwenWendang/img/save.png
FlarumZhongwenWendang/img/saved.png
FlarumZhongwenWendang/img/settings-s.png
FlarumZhongwenWendang/img/settings.png
FlarumZhongwenWendang/img/star.png
FlarumZhongwenWendang/js/__init__.py
FlarumZhongwenWendang/js/epub.js
FlarumZhongwenWendang/js/epub.min.js
FlarumZhongwenWendang/js/epub.min.map
FlarumZhongwenWendang/js/hooks.min.js
FlarumZhongwenWendang/js/hooks.min.map
FlarumZhongwenWendang/js/reader.js
FlarumZhongwenWendang/js/reader.js.map
FlarumZhongwenWendang/js/reader.min.js
FlarumZhongwenWendang/js/reader.min.map
FlarumZhongwenWendang/js/hooks/__init__.py
FlarumZhongwenWendang/js/hooks/extensions/__init__.py
FlarumZhongwenWendang/js/hooks/extensions/highlight.js
FlarumZhongwenWendang/js/libs/__init__.py
FlarumZhongwenWendang/js/libs/jquery.min.js
FlarumZhongwenWendang/js/libs/localforage.min.js
FlarumZhongwenWendang/js/libs/screenfull.js
FlarumZhongwenWendang/js/libs/screenfull.min.js
FlarumZhongwenWendang/js/libs/zip.min.js
FlarumZhongwenWendang/js/plugins/__init__.py
flarum_zhongwen_wendang-2024.3.2.0.dist-info/METADATA
flarum_zhongwen_wendang-2024.3.2.0.dist-info/WHEEL
flarum_zhongwen_wendang-2024.3.2.0.dist-info/entry_points.txt
flarum_zhongwen_wendang-2024.3.2.0.dist-info/top_level.txt
flarum_zhongwen_wendang-2024.3.2.0.dist-info/RECORD
